michi/__init__.py
michi/main.py
michi-0.0.2.dist-info/LICENSE
michi-0.0.2.dist-info/METADATA
michi-0.0.2.dist-info/WHEEL
michi-0.0.2.dist-info/top_level.txt
michi-0.0.2.dist-info/RECORD
